shipyard_dbt/__init__.py
shipyard_dbt/dbt.py
shipyard_dbt/cli/__init__.py
shipyard_dbt/cli/authtest.py
shipyard_dbt/cli/download_logs_artifacts.py
shipyard_dbt/cli/trigger_and_download.py
shipyard_dbt/cli/trigger_job.py
shipyard_dbt-0.2.1.dist-info/METADATA
shipyard_dbt-0.2.1.dist-info/WHEEL
shipyard_dbt-0.2.1.dist-info/top_level.txt
shipyard_dbt-0.2.1.dist-info/RECORD
