Metadata-Version: 2.4
Name: shipyard-dbt
Version: 0.2.1
Requires-Python: >=3.9
Requires-Dist: requests>=2.32.3
Requires-Dist: shipyard-bp-utils>=1.2.0
Requires-Dist: shipyard-templates>=0.8.2
